Metadata-Version: 2.4
Name: adafruit-circuitpython-fakerequests
Version: 1.1.1
Summary: Fake Network Requests helper that retrieves data from a local file.
Author-email: Adafruit Industries <circuitpython@adafruit.com>
License: MIT
Project-URL: Homepage, https://github.com/adafruit/Adafruit_CircuitPython_FakeRequests
Keywords: adafruit,blinka,circuitpython,micropython,fakerequests,fake,requests,file,network,internet,http
Classifier: Intended Audience :: Developers
Classifier: Topic :: Software Development :: Libraries
Classifier: Topic :: Software Development :: Embedded Systems
Classifier: Topic :: System :: Hardware
Classifier: License :: OSI Approved :: MIT License
Classifier: Programming Language :: Python :: 3
License-File: LICENSE
Requires-Dist: Adafruit-Blinka
Provides-Extra: optional
Dynamic: license-file
